email_mcp_server/__init__.py
email_mcp_server/client.py
email_mcp_server/models.py
email_mcp_server/rules.py
email_mcp_server/server.py
email_mcp_server-0.1.0.dist-info/METADATA
email_mcp_server-0.1.0.dist-info/WHEEL
email_mcp_server-0.1.0.dist-info/entry_points.txt
email_mcp_server-0.1.0.dist-info/top_level.txt
email_mcp_server-0.1.0.dist-info/RECORD
